heracless-0.5.1.dist-info/METADATA
heracless-0.5.1.dist-info/WHEEL
heracless-0.5.1.dist-info/licenses/LICENSE
heracless/__init__.py
heracless/cli_tool.py
heracless/fight.py
heracless/heracless_core.cpython-310-darwin.so
heracless/heracless_core.pyi
heracless/rust_backend.py
heracless/utils/__init__.py
heracless/utils/cfg_tree.py
heracless/utils/exceptions.py
heracless/utils/helper.py
heracless/utils/load_func_template.py
heracless/utils/utils.py
heracless-0.5.1.dist-info/RECORD
