Metadata-Version: 2.4
Name: heracless
Version: 0.5.1
Classifier: Development Status :: 4 - Beta
Classifier: Programming Language :: Python :: 3.10
Classifier: Programming Language :: Python :: 3.11
Classifier: Programming Language :: Python :: 3.12
Classifier: Programming Language :: Python :: 3.13
Classifier: Programming Language :: Rust
Requires-Dist: black
Requires-Dist: pyyaml
Requires-Dist: art
Requires-Dist: pytest ; extra == 'dev'
Requires-Dist: pytest-cov ; extra == 'dev'
Requires-Dist: mypy ; extra == 'dev'
Requires-Dist: types-pyyaml ; extra == 'dev'
Requires-Dist: mkdocs>=1.5.0 ; extra == 'doc'
Requires-Dist: mkdocs-material>=9.5.0 ; extra == 'doc'
Requires-Dist: mkdocstrings[python]>=0.24.0 ; extra == 'doc'
Provides-Extra: dev
Provides-Extra: doc
License-File: LICENSE
Summary: Yaml to Dataclass parser for Config files (Rust-powered for performance)
Keywords: YAML,Dataclass,Config,config,config management
Home-Page: https://heracless.io
Author-email: Felix Schelling <felix.schelling@protonmail.com>
Requires-Python: >=3.10
Project-URL: Repository, https://github.com/felixscode/heracless.git
Project-URL: Homepage, https://heracless.io
